renku_lock/__init__.py
renku_lock-2.9.4.dist-info/METADATA
renku_lock-2.9.4.dist-info/WHEEL
renku_lock-2.9.4.dist-info/RECORD
